[
  {"id":"birds-seabirds-1","title":"Sea Birds Part 1","category":"birds","bgGradient":["#0077B6","#00B4D8"],"accentColor":"#0077B6","items":[{"letter":"A","word":"Albatross","emoji":"🐦","bgColor":"#F5F5F5"},{"letter":"B","word":"Booby","emoji":"🐦","bgColor":"#4169E1"},{"letter":"C","word":"Cormorant","emoji":"🐦","bgColor":"#1C1C1C"},{"letter":"D","word":"Diving Petrel","emoji":"🐦","bgColor":"#2F4F4F"},{"letter":"E","word":"Elder Duck","emoji":"🦆","bgColor":"#556B2F"},{"letter":"F","word":"Frigatebird","emoji":"🐦","bgColor":"#1C1C1C"},{"letter":"G","word":"Gannet","emoji":"🐦","bgColor":"#F5F5F5"},{"letter":"H","word":"Herring Gull","emoji":"🐦","bgColor":"#C0C0C0"},{"letter":"I","word":"Indian Skimmer","emoji":"🐦","bgColor":"#1C1C1C"},{"letter":"J","word":"Jaeger","emoji":"🐦","bgColor":"#2F4F4F"},{"letter":"K","word":"Kittiwake","emoji":"🐦","bgColor":"#F5F5F5"},{"letter":"L","word":"Laughing Gull","emoji":"🐦","bgColor":"#C0C0C0"},{"letter":"M","word":"Murre","emoji":"🐦","bgColor":"#1C1C1C"},{"letter":"N","word":"Noddy Tern","emoji":"🐦","bgColor":"#8B4513"},{"letter":"O","word":"Oyster Catcher","emoji":"🐦","bgColor":"#1C1C1C"},{"letter":"P","word":"Puffin","emoji":"🐦","bgColor":"#1C1C1C"},{"letter":"Q","word":"Quahog Gull","emoji":"🐦","bgColor":"#C0C0C0"},{"letter":"R","word":"Razorbill","emoji":"🐦","bgColor":"#1C1C1C"},{"letter":"S","word":"Sooty Tern","emoji":"🐦","bgColor":"#2F4F4F"},{"letter":"T","word":"Tropicbird","emoji":"🐦","bgColor":"#F5F5F5"},{"letter":"U","word":"Uria Guillemot","emoji":"🐦","bgColor":"#1C1C1C"},{"letter":"V","word":"Velvet Scoter","emoji":"🦆","bgColor":"#1C1C1C"},{"letter":"W","word":"Wandering Albatross","emoji":"🐦","bgColor":"#F5F5F5"},{"letter":"X","word":"Xantus Murrelet","emoji":"🐦","bgColor":"#2F4F4F"},{"letter":"Y","word":"Yellow-nosed Albatross","emoji":"🐦","bgColor":"#F5F5F5"},{"letter":"Z","word":"Zigzag Heron","emoji":"🐦","bgColor":"#8B6914"}],"letterDuration":3,"introDuration":3,"outroDuration":3},
  {"id":"birds-hummingbirds-1","title":"Hummingbirds Part 1","category":"birds","bgGradient":["#11998E","#38EF7D"],"accentColor":"#1ABC9C","items":[{"letter":"A","word":"Anna's Hummingbird","emoji":"🐦","bgColor":"#DC143C"},{"letter":"B","word":"Bee Hummingbird","emoji":"🐦","bgColor":"#32CD32"},{"letter":"C","word":"Costa's Hummingbird","emoji":"🐦","bgColor":"#8B008B"},{"letter":"D","word":"Diamond Firetail","emoji":"🐦","bgColor":"#DC143C"},{"letter":"E","word":"Emerald Hummingbird","emoji":"🐦","bgColor":"#228B22"},{"letter":"F","word":"Fiery-throated","emoji":"🐦","bgColor":"#FF4500"},{"letter":"G","word":"Giant Hummingbird","emoji":"🐦","bgColor":"#228B22"},{"letter":"H","word":"Heliomaster","emoji":"🐦","bgColor":"#4169E1"},{"letter":"I","word":"Inca Hummingbird","emoji":"🐦","bgColor":"#FFD700"},{"letter":"J","word":"Jacobin Hummingbird","emoji":"🐦","bgColor":"#F5F5F5"},{"letter":"K","word":"Klamath Hummingbird","emoji":"🐦","bgColor":"#32CD32"},{"letter":"L","word":"Lucifer Hummingbird","emoji":"🐦","bgColor":"#8B008B"},{"letter":"M","word":"Mango Hummingbird","emoji":"🐦","bgColor":"#228B22"},{"letter":"N","word":"Needle-billed","emoji":"🐦","bgColor":"#00CED1"},{"letter":"O","word":"Oasis Hummingbird","emoji":"🐦","bgColor":"#228B22"},{"letter":"P","word":"Purple-throated","emoji":"🐦","bgColor":"#8B008B"},{"letter":"Q","word":"Quetzal Relative","emoji":"🐦","bgColor":"#00CED1"},{"letter":"R","word":"Ruby-throated","emoji":"🐦","bgColor":"#DC143C"},{"letter":"S","word":"Sword-billed","emoji":"🐦","bgColor":"#228B22"},{"letter":"T","word":"Topaz Hummingbird","emoji":"🐦","bgColor":"#FFD700"},{"letter":"U","word":"Ultra Violet Hummer","emoji":"🐦","bgColor":"#8B008B"},{"letter":"V","word":"Violet-crowned","emoji":"🐦","bgColor":"#8B008B"},{"letter":"W","word":"White-eared","emoji":"🐦","bgColor":"#F5F5F5"},{"letter":"X","word":"Xantus Hummingbird","emoji":"🐦","bgColor":"#00CED1"},{"letter":"Y","word":"Yellow Sapphire","emoji":"🐦","bgColor":"#FFD700"},{"letter":"Z","word":"Zigzag Hummingbird","emoji":"🐦","bgColor":"#228B22"}],"letterDuration":3,"introDuration":3,"outroDuration":3},
  {"id":"vehicles-vintage-1","title":"Vintage & Classic Vehicles Part 1","category":"vehicles","bgGradient":["#8B4513","#DEB887"],"accentColor":"#8B4513","items":[{"letter":"A","word":"Ambassador Car","emoji":"🚗","bgColor":"#F5F5F5"},{"letter":"B","word":"Beetle (VW)","emoji":"🚗","bgColor":"#4682B4"},{"letter":"C","word":"Chariot","emoji":"🐴","bgColor":"#DAA520"},{"letter":"D","word":"Double Decker Bus","emoji":"🚌","bgColor":"#DC143C"},{"letter":"E","word":"Essex Coach","emoji":"🚗","bgColor":"#1C1C1C"},{"letter":"F","word":"Ford Model T","emoji":"🚗","bgColor":"#1C1C1C"},{"letter":"G","word":"Gypsy Cart","emoji":"🐴","bgColor":"#8B4513"},{"letter":"H","word":"Horse Carriage","emoji":"🐴","bgColor":"#8B4513"},{"letter":"I","word":"Indian Fiat","emoji":"🚗","bgColor":"#F5F5F5"},{"letter":"J","word":"Jeep Willys","emoji":"🚙","bgColor":"#556B2F"},{"letter":"K","word":"Knight's Horse","emoji":"🐴","bgColor":"#C0C0C0"},{"letter":"L","word":"Locomotive Steam","emoji":"🚂","bgColor":"#1C1C1C"},{"letter":"M","word":"Morris Minor","emoji":"🚗","bgColor":"#228B22"},{"letter":"N","word":"Noble Cart","emoji":"🐴","bgColor":"#FFD700"},{"letter":"O","word":"Old Tram","emoji":"🚃","bgColor":"#DC143C"},{"letter":"P","word":"Padmini Car","emoji":"🚗","bgColor":"#F5F5F5"},{"letter":"Q","word":"Queen's Carriage","emoji":"🐴","bgColor":"#FFD700"},{"letter":"R","word":"Rolls Royce Classic","emoji":"🚗","bgColor":"#C0C0C0"},{"letter":"S","word":"Steam Engine","emoji":"🚂","bgColor":"#1C1C1C"},{"letter":"T","word":"Tonga Cart","emoji":"🐴","bgColor":"#8B4513"},{"letter":"U","word":"Unicycle Penny","emoji":"🚲","bgColor":"#1C1C1C"},{"letter":"V","word":"Victorian Buggy","emoji":"🐴","bgColor":"#8B4513"},{"letter":"W","word":"Wagon Wheel Cart","emoji":"🐴","bgColor":"#8B4513"},{"letter":"X","word":"X-old Bicycle","emoji":"🚲","bgColor":"#1C1C1C"},{"letter":"Y","word":"Yesteryear Bus","emoji":"🚌","bgColor":"#DAA520"},{"letter":"Z","word":"Zephyr Classic","emoji":"🚗","bgColor":"#4682B4"}],"letterDuration":3,"introDuration":3,"outroDuration":3},
  {"id":"vehicles-racing-1","title":"Racing Vehicles Part 1","category":"vehicles","bgGradient":["#C0392B","#E74C3C"],"accentColor":"#E74C3C","items":[{"letter":"A","word":"Aston Martin","emoji":"🏎️","bgColor":"#228B22"},{"letter":"B","word":"Bugatti","emoji":"🏎️","bgColor":"#4169E1"},{"letter":"C","word":"Championship Car","emoji":"🏎️","bgColor":"#DC143C"},{"letter":"D","word":"Drag Racer","emoji":"🏎️","bgColor":"#1C1C1C"},{"letter":"E","word":"Electric Race Car","emoji":"🏎️","bgColor":"#00CED1"},{"letter":"F","word":"Formula One Car","emoji":"🏎️","bgColor":"#DC143C"},{"letter":"G","word":"Go Kart","emoji":"🏎️","bgColor":"#32CD32"},{"letter":"H","word":"Hot Rod","emoji":"🏎️","bgColor":"#FF4500"},{"letter":"I","word":"IndyCar","emoji":"🏎️","bgColor":"#FFD700"},{"letter":"J","word":"Jaguar Racer","emoji":"🏎️","bgColor":"#228B22"},{"letter":"K","word":"Kart Racing","emoji":"🏎️","bgColor":"#DC143C"},{"letter":"L","word":"Lamborghini","emoji":"🏎️","bgColor":"#FFD700"},{"letter":"M","word":"McLaren","emoji":"🏎️","bgColor":"#FF8C00"},{"letter":"N","word":"NASCAR","emoji":"🏎️","bgColor":"#4169E1"},{"letter":"O","word":"Off-road Rally","emoji":"🏎️","bgColor":"#8B4513"},{"letter":"P","word":"Porsche","emoji":"🏎️","bgColor":"#C0C0C0"},{"letter":"Q","word":"Quick Sprint Car","emoji":"🏎️","bgColor":"#FFD700"},{"letter":"R","word":"Rally Car","emoji":"🏎️","bgColor":"#4169E1"},{"letter":"S","word":"Stock Car","emoji":"🏎️","bgColor":"#DC143C"},{"letter":"T","word":"Turbo Racer","emoji":"🏎️","bgColor":"#FF4500"},{"letter":"U","word":"Ultra-fast Car","emoji":"🏎️","bgColor":"#FFD700"},{"letter":"V","word":"V8 Supercar","emoji":"🏎️","bgColor":"#DC143C"},{"letter":"W","word":"WRC Rally Car","emoji":"🏎️","bgColor":"#4169E1"},{"letter":"X","word":"X-treme Racer","emoji":"🏎️","bgColor":"#FF0000"},{"letter":"Y","word":"Yellow Flag Car","emoji":"🏎️","bgColor":"#FFD700"},{"letter":"Z","word":"Zero to Sixty Car","emoji":"🏎️","bgColor":"#1C1C1C"}],"letterDuration":3,"introDuration":3,"outroDuration":3},
  {"id":"vehicles-public-1","title":"Public Transport Part 1","category":"vehicles","bgGradient":["#4B6CB7","#182848"],"accentColor":"#2980B9","items":[{"letter":"A","word":"Airport Shuttle","emoji":"🚌","bgColor":"#4682B4"},{"letter":"B","word":"Bus Rapid Transit","emoji":"🚌","bgColor":"#DC143C"},{"letter":"C","word":"City Bus","emoji":"🚌","bgColor":"#228B22"},{"letter":"D","word":"Double Decker","emoji":"🚌","bgColor":"#DC143C"},{"letter":"E","word":"Electric Tram","emoji":"🚃","bgColor":"#32CD32"},{"letter":"F","word":"Ferry Boat","emoji":"⛴️","bgColor":"#4682B4"},{"letter":"G","word":"Green Bus","emoji":"🚌","bgColor":"#228B22"},{"letter":"H","word":"Highway Express","emoji":"🚌","bgColor":"#DC143C"},{"letter":"I","word":"Interstate Coach","emoji":"🚌","bgColor":"#4682B4"},{"letter":"J","word":"Jitney Bus","emoji":"🚌","bgColor":"#FFD700"},{"letter":"K","word":"Kerala Bus","emoji":"🚌","bgColor":"#DC143C"},{"letter":"L","word":"Light Rail","emoji":"🚃","bgColor":"#4682B4"},{"letter":"M","word":"Metro Rail","emoji":"🚇","bgColor":"#4169E1"},{"letter":"N","word":"Night Bus","emoji":"🚌","bgColor":"#191970"},{"letter":"O","word":"Orange Line Metro","emoji":"🚇","bgColor":"#FF8C00"},{"letter":"P","word":"Pink Line Metro","emoji":"🚇","bgColor":"#FF69B4"},{"letter":"Q","word":"Queue Bus","emoji":"🚌","bgColor":"#4682B4"},{"letter":"R","word":"Rapid Metro","emoji":"🚇","bgColor":"#DC143C"},{"letter":"S","word":"Suburban Train","emoji":"🚃","bgColor":"#4682B4"},{"letter":"T","word":"Trolleybus","emoji":"🚌","bgColor":"#32CD32"},{"letter":"U","word":"Underground Train","emoji":"🚇","bgColor":"#4169E1"},{"letter":"V","word":"Volvo Bus","emoji":"🚌","bgColor":"#DC143C"},{"letter":"W","word":"Water Bus","emoji":"🚤","bgColor":"#4682B4"},{"letter":"X","word":"X-press Bus","emoji":"🚌","bgColor":"#DC143C"},{"letter":"Y","word":"Yellow Bus","emoji":"🚌","bgColor":"#FFD700"},{"letter":"Z","word":"Zone Bus","emoji":"🚌","bgColor":"#228B22"}],"letterDuration":3,"introDuration":3,"outroDuration":3}
]
